nlpretext/__init__.py
nlpretext/_config/__init__.py
nlpretext/_config/config.py
nlpretext/_config/constants.py
nlpretext/_config/stopwords.py
nlpretext/_utils/__init__.py
nlpretext/_utils/daskloader.py
nlpretext/_utils/file_loader.py
nlpretext/_utils/pandasloader.py
nlpretext/_utils/phone_number.py
nlpretext/_utils/stopwords.py
nlpretext/augmentation/__init__.py
nlpretext/augmentation/text_augmentation.py
nlpretext/basic/__init__.py
nlpretext/basic/preprocess.py
nlpretext/cli/__init__.py
nlpretext/cli/__main__.py
nlpretext/cli/preprocess.py
nlpretext/preprocessor.py
nlpretext/py.typed
nlpretext/social/__init__.py
nlpretext/social/preprocess.py
nlpretext/textloader.py
nlpretext/token/__init__.py
nlpretext/token/preprocess.py
nlpretext/token/tokenizer.py
nlpretext-1.2.2.dist-info/LICENSE
nlpretext-1.2.2.dist-info/METADATA
nlpretext-1.2.2.dist-info/WHEEL
nlpretext-1.2.2.dist-info/entry_points.txt
nlpretext-1.2.2.dist-info/RECORD
