Metadata-Version: 2.1
Name: nlpretext
Version: 1.2.2
Summary: All the goto functions you need to handle NLP use-cases, integrated in NLPretext
Home-page: https://github.com/artefactory/NLPretext
License: Apache Software License 2.0
Author: artefactory
Author-email: rafaelle.aygalenq@artefact.com
Requires-Python: >=3.8,<3.11
Classifier: Development Status :: 3 - Alpha
Classifier: Intended Audience :: Developers
Classifier: License :: Other/Proprietary License
Classifier: Operating System :: OS Independent
Classifier: Programming Language :: Python :: 3
Classifier: Programming Language :: Python :: 3.8
Classifier: Programming Language :: Python :: 3.9
Classifier: Programming Language :: Python :: 3.10
Classifier: Topic :: Software Development :: Libraries :: Python Modules
Provides-Extra: torch
Requires-Dist: chardet (>=3.0.4)
Requires-Dist: dask[complete] (>=2021.5.0)
Requires-Dist: distributed (>=2021.5.0)
Requires-Dist: emoji (>=2.0.0)
Requires-Dist: fastparquet (>=0.4.1)
Requires-Dist: flashtext (>=2.7)
Requires-Dist: ftfy (>=4.2.0)
Requires-Dist: importlib_metadata (>=1.6.0) ; python_version < "3.8"
Requires-Dist: mosestokenizer (>=1.1.0)
Requires-Dist: nlpaug (>=1.0.1)
Requires-Dist: nltk (>=3.4.2)
Requires-Dist: numpy (>1.22.0)
Requires-Dist: pandas (>=1.3,<2.0)
Requires-Dist: phonenumbers (>=8.10.12)
Requires-Dist: pillow (>=8.2.1)
Requires-Dist: pyarrow (>=4.0.0)
Requires-Dist: regex (>=2019.8.19)
Requires-Dist: rich (>=10.1.0)
Requires-Dist: sacremoses (>=0.0.13)
Requires-Dist: scikit-learn (>=0.23.2)
Requires-Dist: spacy (>=3.0.5)
Requires-Dist: stop-words (>=2018.7.23)
Requires-Dist: thinc (>=8.0.4)
Requires-Dist: torch (>=1.9.0,<2.0.0) ; extra == "torch"
Requires-Dist: tornado (>=6.0.3)
Requires-Dist: typer[all] (>=0.3.2)
Project-URL: Repository, https://github.com/artefactory/NLPretext
